{
    "description": "file for network node information",
    "netDevice": [
        {
            "image": "/src/assets/router_logo.png",
            "position": {
                "x": 373,
                "y": 219
            },
            "id": 1,
            "id_n": 1
        },
        {
            "id": "1",
            "type": "imageNode",
            "position": {
                "x": 388,
                "y": 195
            },
            "data": {
                "image": "/src/assets/router_logo.png"
            },
            "id_c": 1
        },
        {
            "id": "2",
            "type": "imageNode",
            "position": {
                "x": 390,
                "y": 163
            },
            "data": {
                "image": "/src/assets/router_logo.png"
            },
            "id_c": 1
        },
        {
            "id": "1",
            "type": "imageNode",
            "position": {
                "x": 536,
                "y": 224
            },
            "data": {
                "image": "/src/assets/router_logo.png"
            },
            "id_c": 1
        },
        {
            "id": "2",
            "type": "imageNode",
            "position": {
                "x": 519,
                "y": 166
            },
            "data": {
                "image": "/src/assets/router_logo.png"
            },
            "id_c": 1
        },
        {
            "id": "1",
            "type": "imageNode",
            "position": {
                "x": 494,
                "y": 216
            },
            "data": {
                "image": "/src/assets/router_logo.png"
            },
            "id_c": 1
        },
        {
            "id": "2",
            "type": "imageNode",
            "position": {
                "x": 473,
                "y": 217
            },
            "data": {
                "image": "/src/assets/router_logo.png"
            },
            "id_c": 1
        },
        {
            "id": "1",
            "type": "imageNode",
            "position": {
                "x": 425,
                "y": 273
            },
            "data": {
                "image": "/src/assets/router_logo.png"
            },
            "id_c": 1
        },
        {
            "id": "2",
            "type": "imageNode",
            "position": {
                "x": 580,
                "y": 174
            },
            "data": {
                "image": "/src/assets/router_logo.png"
            },
            "id_c": 2
        },
        {
            "id": "3",
            "type": "imageNode",
            "position": {
                "x": 350,
                "y": 179
            },
            "data": {
                "image": "/src/assets/router_logo.png"
            },
            "id_c": 1
        },
        {
            "id": "1",
            "type": "imageNode",
            "position": {
                "x": 407,
                "y": 258
            },
            "data": {
                "image": "/src/assets/router_logo.png"
            },
            "id_c": 1
        },
        {
            "id": "2",
            "type": "imageNode",
            "position": {
                "x": 349,
                "y": 240
            },
            "data": {
                "image": "/src/assets/router_logo.png"
            },
            "id_c": 2
        },
        {
            "id": "1",
            "type": "imageNode",
            "position": {
                "x": 453,
                "y": 232
            },
            "data": {
                "image": "/src/assets/router_logo.png"
            },
            "id_c": 1
        },
        {
            "id": "2",
            "type": "imageNode",
            "position": {
                "x": 378,
                "y": 251
            },
            "data": {
                "image": "/src/assets/router_logo.png"
            },
            "id_c": 1
        },
        {
            "id": "1",
            "type": "imageNode",
            "position": {
                "x": 353,
                "y": 222
            },
            "data": {
                "image": "/src/assets/router_logo.png"
            },
            "id_c": 1
        },
        {
            "id": "2",
            "type": "imageNode",
            "position": {
                "x": 389,
                "y": 198
            },
            "data": {
                "image": "/src/assets/router_logo.png"
            },
            "id_c": 1
        },
        {
            "id": "1",
            "type": "imageNode",
            "position": {
                "x": 487,
                "y": 231
            },
            "data": {
                "image": "/src/assets/router_logo.png"
            },
            "id_c": 1
        },
        {
            "id": "2",
            "type": "imageNode",
            "position": {
                "x": 233,
                "y": 183
            },
            "data": {
                "image": "/src/assets/router_logo.png"
            },
            "id_c": 1
        },
        {
            "id": "1",
            "type": "imageNode",
            "position": {
                "x": 393,
                "y": 210
            },
            "data": {
                "image": "/src/assets/router_logo.png"
            },
            "id_c": 1
        },
        {
            "id": "2",
            "type": "imageNode",
            "position": {
                "x": 305,
                "y": 192
            },
            "data": {
                "image": "/src/assets/router_logo.png"
            },
            "id_c": 1
        },
        {
            "id": "1",
            "type": "imageNode",
            "position": {
                "x": 508,
                "y": 161
            },
            "data": {
                "image": "/src/assets/router_logo.png"
            },
            "id_c": 1
        },
        {
            "id": "2",
            "type": "imageNode",
            "position": {
                "x": 304,
                "y": 241
            },
            "data": {
                "image": "/src/assets/router_logo.png"
            },
            "id_c": 1
        },
        {
            "id": "1",
            "type": "imageNode",
            "position": {
                "x": 455,
                "y": 184
            },
            "data": {
                "image": "/src/assets/router_logo.png"
            },
            "id_c": 1
        },
        {
            "id": "2",
            "type": "imageNode",
            "position": {
                "x": 285,
                "y": 167
            },
            "data": {
                "image": "/src/assets/router_logo.png"
            },
            "id_c": 1
        }
    ],
    "endDevice": []
}